bwscan/__init__.py
bwscan/client/__init__.py
bwscan/common/__init__.py
bwscan/common/lime.py
bwscan/common/sql.py
bwscan/server/__init__.py
bwscan/server/fax_ocr_unattended.py
bwscan-0.1.dist-info/METADATA
bwscan-0.1.dist-info/WHEEL
bwscan-0.1.dist-info/entry_points.txt
bwscan-0.1.dist-info/top_level.txt
bwscan-0.1.dist-info/RECORD
