Metadata-Version: 2.1
Name: bwscan
Version: 0.1
Summary: # bwscan
Requires-Dist: requests
Requires-Dist: pyyaml
Requires-Dist: o365
Requires-Dist: pytesseract
Requires-Dist: pdf2image
Requires-Dist: tqdm
Requires-Dist: sqlalchemy
Requires-Dist: pymysql
